{
    "0": {
        "loss": 2.3040815824136947,
        "cen_accuracy": 0.1012
    },
    "1": {
        "loss": 1.550075543574251,
        "cen_accuracy": 0.5507,
        "num_clients": 5,
        "accumulated_clients": 5
    },
    "2": {
        "loss": 0.928187547781216,
        "cen_accuracy": 0.6643,
        "num_clients": 5,
        "accumulated_clients": 10
    },
    "3": {
        "loss": 0.717198520898819,
        "cen_accuracy": 0.7169,
        "num_clients": 5,
        "accumulated_clients": 15
    },
    "4": {
        "loss": 0.6778563747581202,
        "cen_accuracy": 0.7516,
        "num_clients": 5,
        "accumulated_clients": 20
    },
    "5": {
        "loss": 0.6625255979478549,
        "cen_accuracy": 0.7465,
        "num_clients": 5,
        "accumulated_clients": 25
    },
    "6": {
        "loss": 0.6315197631383476,
        "cen_accuracy": 0.7652,
        "num_clients": 5,
        "accumulated_clients": 30
    },
    "7": {
        "loss": 0.619811387107776,
        "cen_accuracy": 0.7632,
        "num_clients": 5,
        "accumulated_clients": 35
    },
    "8": {
        "loss": 0.5978424765241032,
        "cen_accuracy": 0.7654,
        "num_clients": 5,
        "accumulated_clients": 40
    },
    "9": {
        "loss": 0.5608378244569888,
        "cen_accuracy": 0.7825,
        "num_clients": 5,
        "accumulated_clients": 45
    },
    "10": {
        "loss": 0.564923944469458,
        "cen_accuracy": 0.7811,
        "num_clients": 5,
        "accumulated_clients": 50
    },
    "11": {
        "loss": 0.5659820765447312,
        "cen_accuracy": 0.7817,
        "num_clients": 5,
        "accumulated_clients": 55
    },
    "12": {
        "loss": 0.5493372703512637,
        "cen_accuracy": 0.7876,
        "num_clients": 5,
        "accumulated_clients": 60
    },
    "13": {
        "loss": 0.5351749237257832,
        "cen_accuracy": 0.7892,
        "num_clients": 5,
        "accumulated_clients": 65
    },
    "14": {
        "loss": 0.5211485213460252,
        "cen_accuracy": 0.799,
        "num_clients": 5,
        "accumulated_clients": 70
    },
    "15": {
        "loss": 0.5482629821799434,
        "cen_accuracy": 0.7985,
        "num_clients": 5,
        "accumulated_clients": 75
    },
    "16": {
        "loss": 0.5100853986823901,
        "cen_accuracy": 0.8083,
        "num_clients": 5,
        "accumulated_clients": 80
    },
    "17": {
        "loss": 0.5097210611493442,
        "cen_accuracy": 0.8088,
        "num_clients": 5,
        "accumulated_clients": 85
    },
    "18": {
        "loss": 0.507795538765173,
        "cen_accuracy": 0.8157,
        "num_clients": 5,
        "accumulated_clients": 90
    },
    "19": {
        "loss": 0.5272961671169574,
        "cen_accuracy": 0.8136,
        "num_clients": 5,
        "accumulated_clients": 95
    },
    "20": {
        "loss": 0.4956399523221647,
        "cen_accuracy": 0.8211,
        "num_clients": 5,
        "accumulated_clients": 100
    },
    "21": {
        "loss": 0.5127335333595642,
        "cen_accuracy": 0.8222,
        "num_clients": 5,
        "accumulated_clients": 105
    },
    "22": {
        "loss": 0.5045841599520022,
        "cen_accuracy": 0.8247,
        "num_clients": 5,
        "accumulated_clients": 110
    },
    "23": {
        "loss": 0.494234042283826,
        "cen_accuracy": 0.8269,
        "num_clients": 5,
        "accumulated_clients": 115
    },
    "24": {
        "loss": 0.4874739552172609,
        "cen_accuracy": 0.8305,
        "num_clients": 5,
        "accumulated_clients": 120
    },
    "25": {
        "loss": 0.47957338445102826,
        "cen_accuracy": 0.8302,
        "num_clients": 5,
        "accumulated_clients": 125
    },
    "26": {
        "loss": 0.4888704361054844,
        "cen_accuracy": 0.8337,
        "num_clients": 5,
        "accumulated_clients": 130
    },
    "27": {
        "loss": 0.4756265678249609,
        "cen_accuracy": 0.8354,
        "num_clients": 5,
        "accumulated_clients": 135
    },
    "28": {
        "loss": 0.4921769043222403,
        "cen_accuracy": 0.8347,
        "num_clients": 5,
        "accumulated_clients": 140
    },
    "29": {
        "loss": 0.5152753104988378,
        "cen_accuracy": 0.8295,
        "num_clients": 5,
        "accumulated_clients": 145
    },
    "30": {
        "loss": 0.49709558648804125,
        "cen_accuracy": 0.8327,
        "num_clients": 5,
        "accumulated_clients": 150
    },
    "31": {
        "loss": 0.47337043680512486,
        "cen_accuracy": 0.8365,
        "num_clients": 5,
        "accumulated_clients": 155
    },
    "32": {
        "loss": 0.5126859538804609,
        "cen_accuracy": 0.8396,
        "num_clients": 5,
        "accumulated_clients": 160
    },
    "33": {
        "loss": 0.46457056029916954,
        "cen_accuracy": 0.8386,
        "num_clients": 5,
        "accumulated_clients": 165
    },
    "34": {
        "loss": 0.4703970974721848,
        "cen_accuracy": 0.8387,
        "num_clients": 5,
        "accumulated_clients": 170
    },
    "35": {
        "loss": 0.4844462714446619,
        "cen_accuracy": 0.8413,
        "num_clients": 5,
        "accumulated_clients": 175
    },
    "36": {
        "loss": 0.48058850944232634,
        "cen_accuracy": 0.8372,
        "num_clients": 5,
        "accumulated_clients": 180
    },
    "37": {
        "loss": 0.4575573736295913,
        "cen_accuracy": 0.8441,
        "num_clients": 5,
        "accumulated_clients": 185
    },
    "38": {
        "loss": 0.45683559830101156,
        "cen_accuracy": 0.8426,
        "num_clients": 5,
        "accumulated_clients": 190
    },
    "39": {
        "loss": 0.47536730373534153,
        "cen_accuracy": 0.8404,
        "num_clients": 5,
        "accumulated_clients": 195
    },
    "40": {
        "loss": 0.46179430412884337,
        "cen_accuracy": 0.8415,
        "num_clients": 5,
        "accumulated_clients": 200
    },
    "41": {
        "loss": 0.45257750365395133,
        "cen_accuracy": 0.8452,
        "num_clients": 5,
        "accumulated_clients": 205
    },
    "42": {
        "loss": 0.4811741145321736,
        "cen_accuracy": 0.8425,
        "num_clients": 5,
        "accumulated_clients": 210
    },
    "43": {
        "loss": 0.48043792482953485,
        "cen_accuracy": 0.8449,
        "num_clients": 5,
        "accumulated_clients": 215
    },
    "44": {
        "loss": 0.4747652664733009,
        "cen_accuracy": 0.8486,
        "num_clients": 5,
        "accumulated_clients": 220
    },
    "45": {
        "loss": 0.46718828280132035,
        "cen_accuracy": 0.8453,
        "num_clients": 5,
        "accumulated_clients": 225
    },
    "46": {
        "loss": 0.46684273408529475,
        "cen_accuracy": 0.8429,
        "num_clients": 5,
        "accumulated_clients": 230
    },
    "47": {
        "loss": 0.46148607539483155,
        "cen_accuracy": 0.8464,
        "num_clients": 5,
        "accumulated_clients": 235
    },
    "48": {
        "loss": 0.4549065556722327,
        "cen_accuracy": 0.8499,
        "num_clients": 5,
        "accumulated_clients": 240
    },
    "49": {
        "loss": 0.4617637855271562,
        "cen_accuracy": 0.8506,
        "num_clients": 5,
        "accumulated_clients": 245
    },
    "50": {
        "loss": 0.45634346499372597,
        "cen_accuracy": 0.8506,
        "num_clients": 5,
        "accumulated_clients": 250
    },
    "51": {
        "loss": 0.44865489210754916,
        "cen_accuracy": 0.8536,
        "num_clients": 5,
        "accumulated_clients": 255
    },
    "52": {
        "loss": 0.43786419011628663,
        "cen_accuracy": 0.8551,
        "num_clients": 5,
        "accumulated_clients": 260
    },
    "53": {
        "loss": 0.44831857382775114,
        "cen_accuracy": 0.8565,
        "num_clients": 5,
        "accumulated_clients": 265
    },
    "54": {
        "loss": 0.4583210905615133,
        "cen_accuracy": 0.8537,
        "num_clients": 5,
        "accumulated_clients": 270
    },
    "55": {
        "loss": 0.4910647829833884,
        "cen_accuracy": 0.8513,
        "num_clients": 5,
        "accumulated_clients": 275
    },
    "56": {
        "loss": 0.4872361029774998,
        "cen_accuracy": 0.8558,
        "num_clients": 5,
        "accumulated_clients": 280
    },
    "57": {
        "loss": 0.44606924768739614,
        "cen_accuracy": 0.8559,
        "num_clients": 5,
        "accumulated_clients": 285
    },
    "58": {
        "loss": 0.46358565526743667,
        "cen_accuracy": 0.8515,
        "num_clients": 5,
        "accumulated_clients": 290
    },
    "59": {
        "loss": 0.46801646619130627,
        "cen_accuracy": 0.8518,
        "num_clients": 5,
        "accumulated_clients": 295
    },
    "60": {
        "loss": 0.4458790476353595,
        "cen_accuracy": 0.8593,
        "num_clients": 5,
        "accumulated_clients": 300
    },
    "61": {
        "loss": 0.4420642131528915,
        "cen_accuracy": 0.8604,
        "num_clients": 5,
        "accumulated_clients": 305
    },
    "62": {
        "loss": 0.44794526605750806,
        "cen_accuracy": 0.8581,
        "num_clients": 5,
        "accumulated_clients": 310
    },
    "63": {
        "loss": 0.45469299601480223,
        "cen_accuracy": 0.8592,
        "num_clients": 5,
        "accumulated_clients": 315
    },
    "64": {
        "loss": 0.46191280816024105,
        "cen_accuracy": 0.856,
        "num_clients": 5,
        "accumulated_clients": 320
    },
    "65": {
        "loss": 0.46255170977629795,
        "cen_accuracy": 0.8579,
        "num_clients": 5,
        "accumulated_clients": 325
    },
    "66": {
        "loss": 0.48079071618830815,
        "cen_accuracy": 0.859,
        "num_clients": 5,
        "accumulated_clients": 330
    },
    "67": {
        "loss": 0.4757141759172796,
        "cen_accuracy": 0.857,
        "num_clients": 5,
        "accumulated_clients": 335
    },
    "68": {
        "loss": 0.4895006597351533,
        "cen_accuracy": 0.8519,
        "num_clients": 5,
        "accumulated_clients": 340
    },
    "69": {
        "loss": 0.4424160179405357,
        "cen_accuracy": 0.8634,
        "num_clients": 5,
        "accumulated_clients": 345
    },
    "70": {
        "loss": 0.48657103210163954,
        "cen_accuracy": 0.8584,
        "num_clients": 5,
        "accumulated_clients": 350
    },
    "71": {
        "loss": 0.48308294892501524,
        "cen_accuracy": 0.8564,
        "num_clients": 5,
        "accumulated_clients": 355
    },
    "72": {
        "loss": 0.47244013079439107,
        "cen_accuracy": 0.8571,
        "num_clients": 5,
        "accumulated_clients": 360
    },
    "73": {
        "loss": 0.4757024634855624,
        "cen_accuracy": 0.8534,
        "num_clients": 5,
        "accumulated_clients": 365
    },
    "74": {
        "loss": 0.46776264789291083,
        "cen_accuracy": 0.8583,
        "num_clients": 5,
        "accumulated_clients": 370
    },
    "75": {
        "loss": 0.44918089419508134,
        "cen_accuracy": 0.8624,
        "num_clients": 5,
        "accumulated_clients": 375
    },
    "76": {
        "loss": 0.45432472069518637,
        "cen_accuracy": 0.8592,
        "num_clients": 5,
        "accumulated_clients": 380
    },
    "77": {
        "loss": 0.4423197888956664,
        "cen_accuracy": 0.8592,
        "num_clients": 5,
        "accumulated_clients": 385
    },
    "78": {
        "loss": 0.4555885639196387,
        "cen_accuracy": 0.8566,
        "num_clients": 5,
        "accumulated_clients": 390
    },
    "79": {
        "loss": 0.4697436661289904,
        "cen_accuracy": 0.8635,
        "num_clients": 5,
        "accumulated_clients": 395
    },
    "80": {
        "loss": 0.4693865897342229,
        "cen_accuracy": 0.8625,
        "num_clients": 5,
        "accumulated_clients": 400
    },
    "81": {
        "loss": 0.46964347808839035,
        "cen_accuracy": 0.8596,
        "num_clients": 5,
        "accumulated_clients": 405
    },
    "82": {
        "loss": 0.4680531767610544,
        "cen_accuracy": 0.8634,
        "num_clients": 5,
        "accumulated_clients": 410
    },
    "83": {
        "loss": 0.4631463133584196,
        "cen_accuracy": 0.8615,
        "num_clients": 5,
        "accumulated_clients": 415
    },
    "84": {
        "loss": 0.49091837618250056,
        "cen_accuracy": 0.8627,
        "num_clients": 5,
        "accumulated_clients": 420
    },
    "85": {
        "loss": 0.48289122708594073,
        "cen_accuracy": 0.8617,
        "num_clients": 5,
        "accumulated_clients": 425
    },
    "86": {
        "loss": 0.47242349486191054,
        "cen_accuracy": 0.8633,
        "num_clients": 5,
        "accumulated_clients": 430
    },
    "87": {
        "loss": 0.4681950016334034,
        "cen_accuracy": 0.8639,
        "num_clients": 5,
        "accumulated_clients": 435
    },
    "88": {
        "loss": 0.478782819589963,
        "cen_accuracy": 0.8645,
        "num_clients": 5,
        "accumulated_clients": 440
    },
    "89": {
        "loss": 0.4968214941481813,
        "cen_accuracy": 0.8587,
        "num_clients": 5,
        "accumulated_clients": 445
    },
    "90": {
        "loss": 0.4869729268688935,
        "cen_accuracy": 0.8608,
        "num_clients": 5,
        "accumulated_clients": 450
    },
    "91": {
        "loss": 0.4553442109768954,
        "cen_accuracy": 0.8656,
        "num_clients": 5,
        "accumulated_clients": 455
    },
    "92": {
        "loss": 0.45501004973539527,
        "cen_accuracy": 0.8535,
        "num_clients": 5,
        "accumulated_clients": 460
    },
    "93": {
        "loss": 0.48252510973296986,
        "cen_accuracy": 0.8665,
        "num_clients": 5,
        "accumulated_clients": 465
    },
    "94": {
        "loss": 0.45891342164514165,
        "cen_accuracy": 0.8573,
        "num_clients": 5,
        "accumulated_clients": 470
    },
    "95": {
        "loss": 0.4581115378882177,
        "cen_accuracy": 0.8672,
        "num_clients": 5,
        "accumulated_clients": 475
    },
    "96": {
        "loss": 0.4708496580917995,
        "cen_accuracy": 0.8609,
        "num_clients": 5,
        "accumulated_clients": 480
    },
    "97": {
        "loss": 0.4606140658806879,
        "cen_accuracy": 0.8689,
        "num_clients": 5,
        "accumulated_clients": 485
    },
    "98": {
        "loss": 0.4616527743518543,
        "cen_accuracy": 0.8638,
        "num_clients": 5,
        "accumulated_clients": 490
    },
    "99": {
        "loss": 0.4831574098846783,
        "cen_accuracy": 0.8664,
        "num_clients": 5,
        "accumulated_clients": 495
    },
    "100": {
        "loss": 0.45541900529648166,
        "cen_accuracy": 0.8671,
        "num_clients": 5,
        "accumulated_clients": 500
    },
    "101": {
        "loss": 0.4771273708976686,
        "cen_accuracy": 0.8639,
        "num_clients": 5,
        "accumulated_clients": 505
    },
    "102": {
        "loss": 0.4562820556778877,
        "cen_accuracy": 0.8672,
        "num_clients": 5,
        "accumulated_clients": 510
    },
    "103": {
        "loss": 0.45435724034905434,
        "cen_accuracy": 0.8693,
        "num_clients": 5,
        "accumulated_clients": 515
    },
    "104": {
        "loss": 0.4623755789079224,
        "cen_accuracy": 0.8717,
        "num_clients": 5,
        "accumulated_clients": 520
    },
    "105": {
        "loss": 0.4551006861316701,
        "cen_accuracy": 0.8661,
        "num_clients": 5,
        "accumulated_clients": 525
    },
    "106": {
        "loss": 0.4592687372391978,
        "cen_accuracy": 0.8649,
        "num_clients": 5,
        "accumulated_clients": 530
    },
    "107": {
        "loss": 0.47068455183325103,
        "cen_accuracy": 0.8646,
        "num_clients": 5,
        "accumulated_clients": 535
    },
    "108": {
        "loss": 0.4523134434375519,
        "cen_accuracy": 0.8626,
        "num_clients": 5,
        "accumulated_clients": 540
    },
    "109": {
        "loss": 0.46087268147224814,
        "cen_accuracy": 0.8705,
        "num_clients": 5,
        "accumulated_clients": 545
    },
    "110": {
        "loss": 0.46951068028474385,
        "cen_accuracy": 0.8728,
        "num_clients": 5,
        "accumulated_clients": 550
    },
    "111": {
        "loss": 0.49636037806019234,
        "cen_accuracy": 0.8679,
        "num_clients": 5,
        "accumulated_clients": 555
    },
    "112": {
        "loss": 0.4839733950555705,
        "cen_accuracy": 0.8615,
        "num_clients": 5,
        "accumulated_clients": 560
    },
    "113": {
        "loss": 0.46718966762145486,
        "cen_accuracy": 0.8638,
        "num_clients": 5,
        "accumulated_clients": 565
    },
    "114": {
        "loss": 0.4818614257838779,
        "cen_accuracy": 0.8681,
        "num_clients": 5,
        "accumulated_clients": 570
    },
    "115": {
        "loss": 0.46397445748408384,
        "cen_accuracy": 0.8688,
        "num_clients": 5,
        "accumulated_clients": 575
    },
    "116": {
        "loss": 0.4839142226039792,
        "cen_accuracy": 0.8684,
        "num_clients": 5,
        "accumulated_clients": 580
    },
    "117": {
        "loss": 0.46537405133437804,
        "cen_accuracy": 0.8696,
        "num_clients": 5,
        "accumulated_clients": 585
    },
    "118": {
        "loss": 0.472119556567349,
        "cen_accuracy": 0.8586,
        "num_clients": 5,
        "accumulated_clients": 590
    },
    "119": {
        "loss": 0.48275131829820883,
        "cen_accuracy": 0.871,
        "num_clients": 5,
        "accumulated_clients": 595
    },
    "120": {
        "loss": 0.4741097260207033,
        "cen_accuracy": 0.8695,
        "num_clients": 5,
        "accumulated_clients": 600
    },
    "121": {
        "loss": 0.49047780100006266,
        "cen_accuracy": 0.872,
        "num_clients": 5,
        "accumulated_clients": 605
    },
    "122": {
        "loss": 0.48120124716633045,
        "cen_accuracy": 0.8694,
        "num_clients": 5,
        "accumulated_clients": 610
    },
    "123": {
        "loss": 0.47411560640929223,
        "cen_accuracy": 0.8687,
        "num_clients": 5,
        "accumulated_clients": 615
    },
    "124": {
        "loss": 0.4748021772922799,
        "cen_accuracy": 0.8709,
        "num_clients": 5,
        "accumulated_clients": 620
    },
    "125": {
        "loss": 0.4798895691554196,
        "cen_accuracy": 0.8692,
        "num_clients": 5,
        "accumulated_clients": 625
    },
    "126": {
        "loss": 0.47622639873919015,
        "cen_accuracy": 0.8665,
        "num_clients": 5,
        "accumulated_clients": 630
    },
    "127": {
        "loss": 0.4644544529029356,
        "cen_accuracy": 0.8667,
        "num_clients": 5,
        "accumulated_clients": 635
    },
    "128": {
        "loss": 0.4728780501661971,
        "cen_accuracy": 0.8624,
        "num_clients": 5,
        "accumulated_clients": 640
    },
    "129": {
        "loss": 0.5429444637018651,
        "cen_accuracy": 0.8623,
        "num_clients": 5,
        "accumulated_clients": 645
    },
    "130": {
        "loss": 0.47670920241993076,
        "cen_accuracy": 0.866,
        "num_clients": 5,
        "accumulated_clients": 650
    },
    "131": {
        "loss": 0.49368231662641315,
        "cen_accuracy": 0.8637,
        "num_clients": 5,
        "accumulated_clients": 655
    },
    "132": {
        "loss": 0.4746996034115267,
        "cen_accuracy": 0.8638,
        "num_clients": 5,
        "accumulated_clients": 660
    },
    "133": {
        "loss": 0.529994831798366,
        "cen_accuracy": 0.8693,
        "num_clients": 5,
        "accumulated_clients": 665
    },
    "134": {
        "loss": 0.5099994465113639,
        "cen_accuracy": 0.8704,
        "num_clients": 5,
        "accumulated_clients": 670
    },
    "135": {
        "loss": 0.45681288054052255,
        "cen_accuracy": 0.8738,
        "num_clients": 5,
        "accumulated_clients": 675
    },
    "136": {
        "loss": 0.4746963951153496,
        "cen_accuracy": 0.8666,
        "num_clients": 5,
        "accumulated_clients": 680
    },
    "137": {
        "loss": 0.47579971370034324,
        "cen_accuracy": 0.867,
        "num_clients": 5,
        "accumulated_clients": 685
    },
    "138": {
        "loss": 0.4767800392672277,
        "cen_accuracy": 0.871,
        "num_clients": 5,
        "accumulated_clients": 690
    },
    "139": {
        "loss": 0.472681837150464,
        "cen_accuracy": 0.869,
        "num_clients": 5,
        "accumulated_clients": 695
    },
    "140": {
        "loss": 0.5150715936296664,
        "cen_accuracy": 0.87,
        "num_clients": 5,
        "accumulated_clients": 700
    },
    "141": {
        "loss": 0.473837092566414,
        "cen_accuracy": 0.8737,
        "num_clients": 5,
        "accumulated_clients": 705
    },
    "142": {
        "loss": 0.4727600242811651,
        "cen_accuracy": 0.8613,
        "num_clients": 5,
        "accumulated_clients": 710
    },
    "143": {
        "loss": 0.45308887332487413,
        "cen_accuracy": 0.8676,
        "num_clients": 5,
        "accumulated_clients": 715
    },
    "144": {
        "loss": 0.46776542631677165,
        "cen_accuracy": 0.8679,
        "num_clients": 5,
        "accumulated_clients": 720
    },
    "145": {
        "loss": 0.48401951300688445,
        "cen_accuracy": 0.8706,
        "num_clients": 5,
        "accumulated_clients": 725
    },
    "146": {
        "loss": 0.46702431182796583,
        "cen_accuracy": 0.8677,
        "num_clients": 5,
        "accumulated_clients": 730
    },
    "147": {
        "loss": 0.4467021568229023,
        "cen_accuracy": 0.8699,
        "num_clients": 5,
        "accumulated_clients": 735
    },
    "148": {
        "loss": 0.4601888430718416,
        "cen_accuracy": 0.873,
        "num_clients": 5,
        "accumulated_clients": 740
    },
    "149": {
        "loss": 0.44969334815161677,
        "cen_accuracy": 0.8739,
        "num_clients": 5,
        "accumulated_clients": 745
    },
    "150": {
        "loss": 0.47853450377147416,
        "cen_accuracy": 0.8663,
        "num_clients": 5,
        "accumulated_clients": 750
    },
    "151": {
        "loss": 0.4608461290550308,
        "cen_accuracy": 0.8707,
        "num_clients": 5,
        "accumulated_clients": 755
    },
    "152": {
        "loss": 0.49427447806055935,
        "cen_accuracy": 0.8684,
        "num_clients": 5,
        "accumulated_clients": 760
    },
    "153": {
        "loss": 0.5114018876141253,
        "cen_accuracy": 0.8714,
        "num_clients": 5,
        "accumulated_clients": 765
    },
    "154": {
        "loss": 0.489799983442401,
        "cen_accuracy": 0.8726,
        "num_clients": 5,
        "accumulated_clients": 770
    },
    "155": {
        "loss": 0.49657244116258314,
        "cen_accuracy": 0.8676,
        "num_clients": 5,
        "accumulated_clients": 775
    },
    "156": {
        "loss": 0.4770020891468936,
        "cen_accuracy": 0.872,
        "num_clients": 5,
        "accumulated_clients": 780
    },
    "157": {
        "loss": 0.46911174136276446,
        "cen_accuracy": 0.8714,
        "num_clients": 5,
        "accumulated_clients": 785
    },
    "158": {
        "loss": 0.4755664399494759,
        "cen_accuracy": 0.8597,
        "num_clients": 5,
        "accumulated_clients": 790
    },
    "159": {
        "loss": 0.49006351098989526,
        "cen_accuracy": 0.8712,
        "num_clients": 5,
        "accumulated_clients": 795
    },
    "160": {
        "loss": 0.4593110516572151,
        "cen_accuracy": 0.8723,
        "num_clients": 5,
        "accumulated_clients": 800
    },
    "161": {
        "loss": 0.5081540188921717,
        "cen_accuracy": 0.8734,
        "num_clients": 5,
        "accumulated_clients": 805
    },
    "162": {
        "loss": 0.48107782065773164,
        "cen_accuracy": 0.8718,
        "num_clients": 5,
        "accumulated_clients": 810
    },
    "163": {
        "loss": 0.45266804091941815,
        "cen_accuracy": 0.8696,
        "num_clients": 5,
        "accumulated_clients": 815
    },
    "164": {
        "loss": 0.4587115285971675,
        "cen_accuracy": 0.8693,
        "num_clients": 5,
        "accumulated_clients": 820
    },
    "165": {
        "loss": 0.48413983269478567,
        "cen_accuracy": 0.8727,
        "num_clients": 5,
        "accumulated_clients": 825
    },
    "166": {
        "loss": 0.5123003679997148,
        "cen_accuracy": 0.8748,
        "num_clients": 5,
        "accumulated_clients": 830
    },
    "167": {
        "loss": 0.5194366541914285,
        "cen_accuracy": 0.8726,
        "num_clients": 5,
        "accumulated_clients": 835
    },
    "168": {
        "loss": 0.49630980385235324,
        "cen_accuracy": 0.8755,
        "num_clients": 5,
        "accumulated_clients": 840
    },
    "169": {
        "loss": 0.5144674602312783,
        "cen_accuracy": 0.8729,
        "num_clients": 5,
        "accumulated_clients": 845
    },
    "170": {
        "loss": 0.4911666226963075,
        "cen_accuracy": 0.8746,
        "num_clients": 5,
        "accumulated_clients": 850
    },
    "171": {
        "loss": 0.5057321004450511,
        "cen_accuracy": 0.8722,
        "num_clients": 5,
        "accumulated_clients": 855
    },
    "172": {
        "loss": 0.5039479561364308,
        "cen_accuracy": 0.8701,
        "num_clients": 5,
        "accumulated_clients": 860
    },
    "173": {
        "loss": 0.5519989707147162,
        "cen_accuracy": 0.8708,
        "num_clients": 5,
        "accumulated_clients": 865
    },
    "174": {
        "loss": 0.4969960034322053,
        "cen_accuracy": 0.873,
        "num_clients": 5,
        "accumulated_clients": 870
    },
    "175": {
        "loss": 0.4930752924146553,
        "cen_accuracy": 0.8695,
        "num_clients": 5,
        "accumulated_clients": 875
    },
    "176": {
        "loss": 0.4950317654389733,
        "cen_accuracy": 0.8644,
        "num_clients": 5,
        "accumulated_clients": 880
    },
    "177": {
        "loss": 0.45814737570457187,
        "cen_accuracy": 0.8674,
        "num_clients": 5,
        "accumulated_clients": 885
    },
    "178": {
        "loss": 0.49970914895970603,
        "cen_accuracy": 0.8716,
        "num_clients": 5,
        "accumulated_clients": 890
    },
    "179": {
        "loss": 0.5031652963056732,
        "cen_accuracy": 0.8719,
        "num_clients": 5,
        "accumulated_clients": 895
    },
    "180": {
        "loss": 0.5068796244196998,
        "cen_accuracy": 0.867,
        "num_clients": 5,
        "accumulated_clients": 900
    },
    "181": {
        "loss": 0.5050663675862951,
        "cen_accuracy": 0.8717,
        "num_clients": 5,
        "accumulated_clients": 905
    },
    "182": {
        "loss": 0.503638673716555,
        "cen_accuracy": 0.8738,
        "num_clients": 5,
        "accumulated_clients": 910
    },
    "183": {
        "loss": 0.484971162883904,
        "cen_accuracy": 0.873,
        "num_clients": 5,
        "accumulated_clients": 915
    },
    "184": {
        "loss": 0.48868401816334966,
        "cen_accuracy": 0.873,
        "num_clients": 5,
        "accumulated_clients": 920
    },
    "185": {
        "loss": 0.5630926287497956,
        "cen_accuracy": 0.8686,
        "num_clients": 5,
        "accumulated_clients": 925
    },
    "186": {
        "loss": 0.5081314332307146,
        "cen_accuracy": 0.8712,
        "num_clients": 5,
        "accumulated_clients": 930
    },
    "187": {
        "loss": 0.49395013852907826,
        "cen_accuracy": 0.8694,
        "num_clients": 5,
        "accumulated_clients": 935
    },
    "188": {
        "loss": 0.5107993658382101,
        "cen_accuracy": 0.873,
        "num_clients": 5,
        "accumulated_clients": 940
    },
    "189": {
        "loss": 0.5101872910968602,
        "cen_accuracy": 0.87,
        "num_clients": 5,
        "accumulated_clients": 945
    },
    "190": {
        "loss": 0.5133735505988994,
        "cen_accuracy": 0.8693,
        "num_clients": 5,
        "accumulated_clients": 950
    },
    "191": {
        "loss": 0.47956801423678,
        "cen_accuracy": 0.8778,
        "num_clients": 5,
        "accumulated_clients": 955
    },
    "192": {
        "loss": 0.5251216559459607,
        "cen_accuracy": 0.8706,
        "num_clients": 5,
        "accumulated_clients": 960
    },
    "193": {
        "loss": 0.5118132522835518,
        "cen_accuracy": 0.8693,
        "num_clients": 5,
        "accumulated_clients": 965
    },
    "194": {
        "loss": 0.5377409448043797,
        "cen_accuracy": 0.8663,
        "num_clients": 5,
        "accumulated_clients": 970
    },
    "195": {
        "loss": 0.5218612468613985,
        "cen_accuracy": 0.8706,
        "num_clients": 5,
        "accumulated_clients": 975
    },
    "196": {
        "loss": 0.5117902289302395,
        "cen_accuracy": 0.8713,
        "num_clients": 5,
        "accumulated_clients": 980
    },
    "197": {
        "loss": 0.5287634911366735,
        "cen_accuracy": 0.8672,
        "num_clients": 5,
        "accumulated_clients": 985
    },
    "198": {
        "loss": 0.4990908443308867,
        "cen_accuracy": 0.8687,
        "num_clients": 5,
        "accumulated_clients": 990
    },
    "199": {
        "loss": 0.5670043411441504,
        "cen_accuracy": 0.8711,
        "num_clients": 5,
        "accumulated_clients": 995
    },
    "200": {
        "loss": 0.5088529952894003,
        "cen_accuracy": 0.8674,
        "num_clients": 5,
        "accumulated_clients": 1000
    },
    "201": {
        "loss": 0.49863972097111586,
        "cen_accuracy": 0.8664,
        "num_clients": 5,
        "accumulated_clients": 1005
    },
    "202": {
        "loss": 0.49846028305661566,
        "cen_accuracy": 0.873,
        "num_clients": 5,
        "accumulated_clients": 1010
    },
    "203": {
        "loss": 0.5191843095726479,
        "cen_accuracy": 0.8717,
        "num_clients": 5,
        "accumulated_clients": 1015
    },
    "204": {
        "loss": 0.5421249422664269,
        "cen_accuracy": 0.8734,
        "num_clients": 5,
        "accumulated_clients": 1020
    },
    "205": {
        "loss": 0.4897280209742415,
        "cen_accuracy": 0.8714,
        "num_clients": 5,
        "accumulated_clients": 1025
    },
    "206": {
        "loss": 0.54718656704044,
        "cen_accuracy": 0.8746,
        "num_clients": 5,
        "accumulated_clients": 1030
    },
    "207": {
        "loss": 0.5591860782628814,
        "cen_accuracy": 0.871,
        "num_clients": 5,
        "accumulated_clients": 1035
    },
    "208": {
        "loss": 0.5535088774090567,
        "cen_accuracy": 0.8727,
        "num_clients": 5,
        "accumulated_clients": 1040
    },
    "209": {
        "loss": 0.5646508860345275,
        "cen_accuracy": 0.8705,
        "num_clients": 5,
        "accumulated_clients": 1045
    },
    "210": {
        "loss": 0.5272226993458721,
        "cen_accuracy": 0.8756,
        "num_clients": 5,
        "accumulated_clients": 1050
    },
    "211": {
        "loss": 0.5193056746984062,
        "cen_accuracy": 0.8727,
        "num_clients": 5,
        "accumulated_clients": 1055
    },
    "212": {
        "loss": 0.5209495291685144,
        "cen_accuracy": 0.876,
        "num_clients": 5,
        "accumulated_clients": 1060
    },
    "213": {
        "loss": 0.5052466556525078,
        "cen_accuracy": 0.8718,
        "num_clients": 5,
        "accumulated_clients": 1065
    },
    "214": {
        "loss": 0.4850824800090858,
        "cen_accuracy": 0.8729,
        "num_clients": 5,
        "accumulated_clients": 1070
    },
    "215": {
        "loss": 0.5236459025345481,
        "cen_accuracy": 0.8717,
        "num_clients": 5,
        "accumulated_clients": 1075
    },
    "216": {
        "loss": 0.5162050093348605,
        "cen_accuracy": 0.8694,
        "num_clients": 5,
        "accumulated_clients": 1080
    },
    "217": {
        "loss": 0.48706512185283746,
        "cen_accuracy": 0.868,
        "num_clients": 5,
        "accumulated_clients": 1085
    },
    "218": {
        "loss": 0.48465457376533044,
        "cen_accuracy": 0.8727,
        "num_clients": 5,
        "accumulated_clients": 1090
    },
    "219": {
        "loss": 0.5120075784695034,
        "cen_accuracy": 0.8694,
        "num_clients": 5,
        "accumulated_clients": 1095
    },
    "220": {
        "loss": 0.5354989675192026,
        "cen_accuracy": 0.8714,
        "num_clients": 5,
        "accumulated_clients": 1100
    },
    "221": {
        "loss": 0.5197887759203442,
        "cen_accuracy": 0.8687,
        "num_clients": 5,
        "accumulated_clients": 1105
    },
    "222": {
        "loss": 0.5099539912808627,
        "cen_accuracy": 0.8733,
        "num_clients": 5,
        "accumulated_clients": 1110
    },
    "223": {
        "loss": 0.5281473911774996,
        "cen_accuracy": 0.8757,
        "num_clients": 5,
        "accumulated_clients": 1115
    },
    "224": {
        "loss": 0.5085224935088676,
        "cen_accuracy": 0.8705,
        "num_clients": 5,
        "accumulated_clients": 1120
    },
    "225": {
        "loss": 0.4826008892430665,
        "cen_accuracy": 0.8698,
        "num_clients": 5,
        "accumulated_clients": 1125
    },
    "226": {
        "loss": 0.5213827865239912,
        "cen_accuracy": 0.8727,
        "num_clients": 5,
        "accumulated_clients": 1130
    },
    "227": {
        "loss": 0.5188877760602263,
        "cen_accuracy": 0.8724,
        "num_clients": 5,
        "accumulated_clients": 1135
    },
    "228": {
        "loss": 0.5133536329594093,
        "cen_accuracy": 0.87,
        "num_clients": 5,
        "accumulated_clients": 1140
    },
    "229": {
        "loss": 0.5180867180799524,
        "cen_accuracy": 0.8755,
        "num_clients": 5,
        "accumulated_clients": 1145
    },
    "230": {
        "loss": 0.502924017584362,
        "cen_accuracy": 0.8773,
        "num_clients": 5,
        "accumulated_clients": 1150
    },
    "231": {
        "loss": 0.5854339900846108,
        "cen_accuracy": 0.8692,
        "num_clients": 5,
        "accumulated_clients": 1155
    },
    "232": {
        "loss": 0.5343075850948739,
        "cen_accuracy": 0.8749,
        "num_clients": 5,
        "accumulated_clients": 1160
    },
    "233": {
        "loss": 0.5031655102182692,
        "cen_accuracy": 0.8714,
        "num_clients": 5,
        "accumulated_clients": 1165
    },
    "234": {
        "loss": 0.5454271898482935,
        "cen_accuracy": 0.8718,
        "num_clients": 5,
        "accumulated_clients": 1170
    },
    "235": {
        "loss": 0.5006101896968512,
        "cen_accuracy": 0.8757,
        "num_clients": 5,
        "accumulated_clients": 1175
    },
    "236": {
        "loss": 0.5720985734972138,
        "cen_accuracy": 0.8711,
        "num_clients": 5,
        "accumulated_clients": 1180
    },
    "237": {
        "loss": 0.5642926369707424,
        "cen_accuracy": 0.8765,
        "num_clients": 5,
        "accumulated_clients": 1185
    },
    "238": {
        "loss": 0.552354592175339,
        "cen_accuracy": 0.8631,
        "num_clients": 5,
        "accumulated_clients": 1190
    },
    "239": {
        "loss": 0.554582339898942,
        "cen_accuracy": 0.8744,
        "num_clients": 5,
        "accumulated_clients": 1195
    },
    "240": {
        "loss": 0.5398579604459551,
        "cen_accuracy": 0.8766,
        "num_clients": 5,
        "accumulated_clients": 1200
    },
    "241": {
        "loss": 0.5381726965117759,
        "cen_accuracy": 0.8713,
        "num_clients": 5,
        "accumulated_clients": 1205
    },
    "242": {
        "loss": 0.5765475930390171,
        "cen_accuracy": 0.8718,
        "num_clients": 5,
        "accumulated_clients": 1210
    },
    "243": {
        "loss": 0.5138203882085629,
        "cen_accuracy": 0.8767,
        "num_clients": 5,
        "accumulated_clients": 1215
    },
    "244": {
        "loss": 0.5275481740911357,
        "cen_accuracy": 0.8726,
        "num_clients": 5,
        "accumulated_clients": 1220
    },
    "245": {
        "loss": 0.547402368917966,
        "cen_accuracy": 0.878,
        "num_clients": 5,
        "accumulated_clients": 1225
    },
    "246": {
        "loss": 0.5156276733361589,
        "cen_accuracy": 0.8768,
        "num_clients": 5,
        "accumulated_clients": 1230
    },
    "247": {
        "loss": 0.5539932398917005,
        "cen_accuracy": 0.8744,
        "num_clients": 5,
        "accumulated_clients": 1235
    },
    "248": {
        "loss": 0.5559024017113752,
        "cen_accuracy": 0.8758,
        "num_clients": 5,
        "accumulated_clients": 1240
    },
    "249": {
        "loss": 0.5656792364550379,
        "cen_accuracy": 0.874,
        "num_clients": 5,
        "accumulated_clients": 1245
    },
    "250": {
        "loss": 0.5923388384270687,
        "cen_accuracy": 0.8778,
        "num_clients": 5,
        "accumulated_clients": 1250
    }
}